datamodel_code_generator/__init__.py
datamodel_code_generator/__main__.py
datamodel_code_generator/arguments.py
datamodel_code_generator/cli_options.py
datamodel_code_generator/config.py
datamodel_code_generator/enums.py
datamodel_code_generator/format.py
datamodel_code_generator/http.py
datamodel_code_generator/imports.py
datamodel_code_generator/input_model.py
datamodel_code_generator/prompt.py
datamodel_code_generator/prompt_data.py
datamodel_code_generator/py.typed
datamodel_code_generator/pydantic_patch.py
datamodel_code_generator/reference.py
datamodel_code_generator/types.py
datamodel_code_generator/util.py
datamodel_code_generator/watch.py
datamodel_code_generator/_types/__init__.py
datamodel_code_generator/_types/generate_config_dict.py
datamodel_code_generator/_types/parse_config_dict.py
datamodel_code_generator/_types/parser_config_dicts.py
datamodel_code_generator/model/__init__.py
datamodel_code_generator/model/_types.py
datamodel_code_generator/model/base.py
datamodel_code_generator/model/dataclass.py
datamodel_code_generator/model/enum.py
datamodel_code_generator/model/imports.py
datamodel_code_generator/model/msgspec.py
datamodel_code_generator/model/scalar.py
datamodel_code_generator/model/type_alias.py
datamodel_code_generator/model/typed_dict.py
datamodel_code_generator/model/types.py
datamodel_code_generator/model/union.py
datamodel_code_generator/model/pydantic/__init__.py
datamodel_code_generator/model/pydantic/base_model.py
datamodel_code_generator/model/pydantic/custom_root_type.py
datamodel_code_generator/model/pydantic/imports.py
datamodel_code_generator/model/pydantic/types.py
datamodel_code_generator/model/pydantic_v2/__init__.py
datamodel_code_generator/model/pydantic_v2/base_model.py
datamodel_code_generator/model/pydantic_v2/dataclass.py
datamodel_code_generator/model/pydantic_v2/imports.py
datamodel_code_generator/model/pydantic_v2/root_model.py
datamodel_code_generator/model/pydantic_v2/root_model_type_alias.py
datamodel_code_generator-0.51.0.dist-info/METADATA
datamodel_code_generator-0.51.0.dist-info/WHEEL
datamodel_code_generator-0.51.0.dist-info/entry_points.txt
datamodel_code_generator-0.51.0.dist-info/licenses/LICENSE
datamodel_code_generator-0.51.0.dist-info/RECORD
