Metadata-Version: 2.4
Name: datamodel-code-generator
Version: 0.51.0
Summary: Datamodel Code Generator
Project-URL: Homepage, https://github.com/koxudaxi/datamodel-code-generator
Project-URL: Source, https://github.com/koxudaxi/datamodel-code-generator
Author-email: Koudai Aono <koxudaxi@gmail.com>
License-Expression: MIT
License-File: LICENSE
Classifier: Development Status :: 4 - Beta
Classifier: License :: OSI Approved :: MIT License
Classifier: Natural Language :: English
Classifier: Programming Language :: Python :: 3 :: Only
Classifier: Programming Language :: Python :: 3.10
Classifier: Programming Language :: Python :: 3.11
Classifier: Programming Language :: Python :: 3.12
Classifier: Programming Language :: Python :: 3.13
Classifier: Programming Language :: Python :: 3.14
Classifier: Programming Language :: Python :: Implementation :: CPython
Requires-Python: >=3.10
Requires-Dist: argcomplete<4,>=2.10.1
Requires-Dist: black>=19.10b0
Requires-Dist: genson<2,>=1.2.1
Requires-Dist: inflect<8,>=4.1
Requires-Dist: isort<8,>=4.3.21
Requires-Dist: jinja2<4,>=2.10.1
Requires-Dist: packaging
Requires-Dist: pydantic>=1.5
Requires-Dist: pyyaml>=6.0.1
Requires-Dist: tomli<3,>=2.2.1; python_version <= '3.11'
Provides-Extra: all
Requires-Dist: graphql-core>=3.2.3; extra == 'all'
Requires-Dist: httpx>=0.24.1; extra == 'all'
Requires-Dist: openapi-spec-validator<0.8,>=0.2.8; extra == 'all'
Requires-Dist: prance>=0.18.2; extra == 'all'
Requires-Dist: pysnooper<2,>=0.4.1; extra == 'all'
Requires-Dist: ruff>=0.9.10; extra == 'all'
Requires-Dist: watchfiles>=1.1; extra == 'all'
Provides-Extra: debug
Requires-Dist: pysnooper<2,>=0.4.1; extra == 'debug'
Provides-Extra: graphql
Requires-Dist: graphql-core>=3.2.3; extra == 'graphql'
Provides-Extra: http
Requires-Dist: httpx>=0.24.1; extra == 'http'
Provides-Extra: ruff
Requires-Dist: ruff>=0.9.10; extra == 'ruff'
Provides-Extra: validation
Requires-Dist: openapi-spec-validator<0.8,>=0.2.8; extra == 'validation'
Requires-Dist: prance>=0.18.2; extra == 'validation'
Provides-Extra: watch
Requires-Dist: watchfiles>=1.1; extra == 'watch'
